<?xml version='1.0' encoding='UTF-8'?>
<vocabulaires>
  <MOT>
    <mot-unique>ااهاا</mot-unique>
    <frequence-mot>1</frequence-mot>
  </MOT>
  <MOT>
    <mot-unique>ابصر</mot-unique>
    <frequence-mot>1</frequence-mot>
  </MOT>
  <MOT>
    <mot-unique>ابيعه</mot-unique>
    <frequence-mot>1</frequence-mot>
  </MOT>
  <MOT>
    <mot-unique>اتخدشت</mot-unique>
    <frequence-mot>1</frequence-mot>
  </MOT>
  <MOT>
    <mot-unique>اتخربطت</mot-unique>
    <frequence-mot>1</frequence-mot>
  </MOT>
  <MOT>
    <mot-unique>اتعودو</mot-unique>
    <frequence-mot>1</frequence-mot>
  </MOT>
  <MOT>
    <mot-unique>اتفقد</mot-unique>
    <frequence-mot>1</frequence-mot>
  </MOT>
  <MOT>
    <mot-unique>اتقاطع</mot-unique>
    <frequence-mot>1</frequence-mot>
  </MOT>
  <MOT>
    <mot-unique>اتمني</mot-unique>
    <frequence-mot>1</frequence-mot>
  </MOT>
  <MOT>
    <mot-unique>اجتمع</mot-unique>
    <frequence-mot>1</frequence-mot>
  </MOT>
  <MOT>
    <mot-unique>احتياطاً</mot-unique>
    <frequence-mot>1</frequence-mot>
  </MOT>
  <MOT>
    <mot-unique>احكولنا</mot-unique>
    <frequence-mot>1</frequence-mot>
  </MOT>
  <MOT>
    <mot-unique>اختياركو</mot-unique>
    <frequence-mot>1</frequence-mot>
  </MOT>
  <MOT>
    <mot-unique>اخسن</mot-unique>
    <frequence-mot>1</frequence-mot>
  </MOT>
  <MOT>
    <mot-unique>ارضي</mot-unique>
    <frequence-mot>1</frequence-mot>
  </MOT>
  <MOT>
    <mot-unique>ارنلها</mot-unique>
    <frequence-mot>1</frequence-mot>
  </MOT>
  <MOT>
    <mot-unique>استفيد</mot-unique>
    <frequence-mot>1</frequence-mot>
  </MOT>
  <MOT>
    <mot-unique>استمعت</mot-unique>
    <frequence-mot>1</frequence-mot>
  </MOT>
  <MOT>
    <mot-unique>استوى</mot-unique>
    <frequence-mot>1</frequence-mot>
  </MOT>
  <MOT>
    <mot-unique>اسماءهم</mot-unique>
    <frequence-mot>1</frequence-mot>
  </MOT>
  <MOT>
    <mot-unique>اصحى</mot-unique>
    <frequence-mot>1</frequence-mot>
  </MOT>
  <MOT>
    <mot-unique>اضمن</mot-unique>
    <frequence-mot>1</frequence-mot>
  </MOT>
  <MOT>
    <mot-unique>اطلعهم</mot-unique>
    <frequence-mot>1</frequence-mot>
  </MOT>
  <MOT>
    <mot-unique>اطنعشر</mot-unique>
    <frequence-mot>1</frequence-mot>
  </MOT>
  <MOT>
    <mot-unique>اعرضها</mot-unique>
    <frequence-mot>1</frequence-mot>
  </MOT>
  <MOT>
    <mot-unique>اععملها</mot-unique>
    <frequence-mot>1</frequence-mot>
  </MOT>
  <MOT>
    <mot-unique>افرجيها</mot-unique>
    <frequence-mot>1</frequence-mot>
  </MOT>
  <MOT>
    <mot-unique>الاحرة</mot-unique>
    <frequence-mot>1</frequence-mot>
  </MOT>
  <MOT>
    <mot-unique>البراندات</mot-unique>
    <frequence-mot>1</frequence-mot>
  </MOT>
  <MOT>
    <mot-unique>البهارات</mot-unique>
    <frequence-mot>1</frequence-mot>
  </MOT>
  <MOT>
    <mot-unique>البوتس</mot-unique>
    <frequence-mot>1</frequence-mot>
  </MOT>
  <MOT>
    <mot-unique>البوزا</mot-unique>
    <frequence-mot>1</frequence-mot>
  </MOT>
  <MOT>
    <mot-unique>الجاج</mot-unique>
    <frequence-mot>1</frequence-mot>
  </MOT>
  <MOT>
    <mot-unique>الجكومة</mot-unique>
    <frequence-mot>1</frequence-mot>
  </MOT>
  <MOT>
    <mot-unique>الجكيت</mot-unique>
    <frequence-mot>1</frequence-mot>
  </MOT>
  <MOT>
    <mot-unique>الحكي</mot-unique>
    <frequence-mot>1</frequence-mot>
  </MOT>
  <MOT>
    <mot-unique>الخضرا</mot-unique>
    <frequence-mot>1</frequence-mot>
  </MOT>
  <MOT>
    <mot-unique>الرحب</mot-unique>
    <frequence-mot>1</frequence-mot>
  </MOT>
  <MOT>
    <mot-unique>السفربيزبط</mot-unique>
    <frequence-mot>1</frequence-mot>
  </MOT>
  <MOT>
    <mot-unique>الشفير</mot-unique>
    <frequence-mot>1</frequence-mot>
  </MOT>
  <MOT>
    <mot-unique>الشنتيتين</mot-unique>
    <frequence-mot>1</frequence-mot>
  </MOT>
  <MOT>
    <mot-unique>الصخرة</mot-unique>
    <frequence-mot>1</frequence-mot>
  </MOT>
  <MOT>
    <mot-unique>الصراف</mot-unique>
    <frequence-mot>2</frequence-mot>
  </MOT>
  <MOT>
    <mot-unique>الطريقل</mot-unique>
    <frequence-mot>1</frequence-mot>
  </MOT>
  <MOT>
    <mot-unique>العاليم</mot-unique>
    <frequence-mot>1</frequence-mot>
  </MOT>
  <MOT>
    <mot-unique>العرباية</mot-unique>
    <frequence-mot>1</frequence-mot>
  </MOT>
  <MOT>
    <mot-unique>العلمية</mot-unique>
    <frequence-mot>1</frequence-mot>
  </MOT>
  <MOT>
    <mot-unique>العيدية</mot-unique>
    <frequence-mot>1</frequence-mot>
  </MOT>
  <MOT>
    <mot-unique>الفتسان</mot-unique>
    <frequence-mot>1</frequence-mot>
  </MOT>
  <MOT>
    <mot-unique>الفراولة</mot-unique>
    <frequence-mot>1</frequence-mot>
  </MOT>
  <MOT>
    <mot-unique>الكريدور</mot-unique>
    <frequence-mot>1</frequence-mot>
  </MOT>
  <MOT>
    <mot-unique>الليوم</mot-unique>
    <frequence-mot>1</frequence-mot>
  </MOT>
  <MOT>
    <mot-unique>المسارات</mot-unique>
    <frequence-mot>1</frequence-mot>
  </MOT>
  <MOT>
    <mot-unique>المستمر</mot-unique>
    <frequence-mot>1</frequence-mot>
  </MOT>
  <MOT>
    <mot-unique>المفريدة</mot-unique>
    <frequence-mot>1</frequence-mot>
  </MOT>
  <MOT>
    <mot-unique>النقاط</mot-unique>
    <frequence-mot>1</frequence-mot>
  </MOT>
  <MOT>
    <mot-unique>امشوا</mot-unique>
    <frequence-mot>1</frequence-mot>
  </MOT>
  <MOT>
    <mot-unique>انتقتلت</mot-unique>
    <frequence-mot>1</frequence-mot>
  </MOT>
  <MOT>
    <mot-unique>انخلع</mot-unique>
    <frequence-mot>1</frequence-mot>
  </MOT>
  <MOT>
    <mot-unique>انسرقو</mot-unique>
    <frequence-mot>2</frequence-mot>
  </MOT>
  <MOT>
    <mot-unique>انكو</mot-unique>
    <frequence-mot>2</frequence-mot>
  </MOT>
  <MOT>
    <mot-unique>اهاا</mot-unique>
    <frequence-mot>1</frequence-mot>
  </MOT>
  <MOT>
    <mot-unique>باحجام</mot-unique>
    <frequence-mot>1</frequence-mot>
  </MOT>
  <MOT>
    <mot-unique>باسمك</mot-unique>
    <frequence-mot>1</frequence-mot>
  </MOT>
  <MOT>
    <mot-unique>باشياء</mot-unique>
    <frequence-mot>1</frequence-mot>
  </MOT>
  <MOT>
    <mot-unique>باعتقادي</mot-unique>
    <frequence-mot>1</frequence-mot>
  </MOT>
  <MOT>
    <mot-unique>بالتحلاية</mot-unique>
    <frequence-mot>1</frequence-mot>
  </MOT>
  <MOT>
    <mot-unique>بالتسليم</mot-unique>
    <frequence-mot>1</frequence-mot>
  </MOT>
  <MOT>
    <mot-unique>بالسماء</mot-unique>
    <frequence-mot>1</frequence-mot>
  </MOT>
  <MOT>
    <mot-unique>بالعطلات</mot-unique>
    <frequence-mot>1</frequence-mot>
  </MOT>
  <MOT>
    <mot-unique>بالفاكس</mot-unique>
    <frequence-mot>1</frequence-mot>
  </MOT>
  <MOT>
    <mot-unique>بالنطقة</mot-unique>
    <frequence-mot>1</frequence-mot>
  </MOT>
  <MOT>
    <mot-unique>بتتصلي</mot-unique>
    <frequence-mot>1</frequence-mot>
  </MOT>
  <MOT>
    <mot-unique>بتتقاطع</mot-unique>
    <frequence-mot>1</frequence-mot>
  </MOT>
  <MOT>
    <mot-unique>بتحرك</mot-unique>
    <frequence-mot>1</frequence-mot>
  </MOT>
  <MOT>
    <mot-unique>بتحول</mot-unique>
    <frequence-mot>1</frequence-mot>
  </MOT>
  <MOT>
    <mot-unique>بتستاهل</mot-unique>
    <frequence-mot>1</frequence-mot>
  </MOT>
  <MOT>
    <mot-unique>بتسعينات</mot-unique>
    <frequence-mot>1</frequence-mot>
  </MOT>
  <MOT>
    <mot-unique>بتصماميم</mot-unique>
    <frequence-mot>1</frequence-mot>
  </MOT>
  <MOT>
    <mot-unique>بتهتم</mot-unique>
    <frequence-mot>1</frequence-mot>
  </MOT>
  <MOT>
    <mot-unique>بتوخذ</mot-unique>
    <frequence-mot>1</frequence-mot>
  </MOT>
  <MOT>
    <mot-unique>بتوكلو</mot-unique>
    <frequence-mot>1</frequence-mot>
  </MOT>
  <MOT>
    <mot-unique>بثمن</mot-unique>
    <frequence-mot>1</frequence-mot>
  </MOT>
  <MOT>
    <mot-unique>بحلقي</mot-unique>
    <frequence-mot>1</frequence-mot>
  </MOT>
  <MOT>
    <mot-unique>بخمسطعش</mot-unique>
    <frequence-mot>1</frequence-mot>
  </MOT>
  <MOT>
    <mot-unique>بر</mot-unique>
    <frequence-mot>1</frequence-mot>
  </MOT>
  <MOT>
    <mot-unique>بروان</mot-unique>
    <frequence-mot>1</frequence-mot>
  </MOT>
  <MOT>
    <mot-unique>بريوح</mot-unique>
    <frequence-mot>1</frequence-mot>
  </MOT>
  <MOT>
    <mot-unique>بستاهل</mot-unique>
    <frequence-mot>1</frequence-mot>
  </MOT>
  <MOT>
    <mot-unique>بشنتتة</mot-unique>
    <frequence-mot>1</frequence-mot>
  </MOT>
  <MOT>
    <mot-unique>بشنتتي</mot-unique>
    <frequence-mot>2</frequence-mot>
  </MOT>
  <MOT>
    <mot-unique>بضعف</mot-unique>
    <frequence-mot>1</frequence-mot>
  </MOT>
  <MOT>
    <mot-unique>بطارتي</mot-unique>
    <frequence-mot>1</frequence-mot>
  </MOT>
  <MOT>
    <mot-unique>بعضر</mot-unique>
    <frequence-mot>1</frequence-mot>
  </MOT>
  <MOT>
    <mot-unique>بفتحه</mot-unique>
    <frequence-mot>1</frequence-mot>
  </MOT>
  <MOT>
    <mot-unique>بقدراخذ</mot-unique>
    <frequence-mot>1</frequence-mot>
  </MOT>
  <MOT>
    <mot-unique>بقدرانظف</mot-unique>
    <frequence-mot>1</frequence-mot>
  </MOT>
  <MOT>
    <mot-unique>بقطة</mot-unique>
    <frequence-mot>1</frequence-mot>
  </MOT>
  <MOT>
    <mot-unique>بقلب</mot-unique>
    <frequence-mot>1</frequence-mot>
  </MOT>
  <MOT>
    <mot-unique>بمغلف</mot-unique>
    <frequence-mot>1</frequence-mot>
  </MOT>
  <MOT>
    <mot-unique>بناطيل</mot-unique>
    <frequence-mot>1</frequence-mot>
  </MOT>
  <MOT>
    <mot-unique>بنبلش</mot-unique>
    <frequence-mot>1</frequence-mot>
  </MOT>
  <MOT>
    <mot-unique>بنحط</mot-unique>
    <frequence-mot>1</frequence-mot>
  </MOT>
  <MOT>
    <mot-unique>بنستخد</mot-unique>
    <frequence-mot>1</frequence-mot>
  </MOT>
  <MOT>
    <mot-unique>بنسميه</mot-unique>
    <frequence-mot>1</frequence-mot>
  </MOT>
  <MOT>
    <mot-unique>بهدف</mot-unique>
    <frequence-mot>1</frequence-mot>
  </MOT>
  <MOT>
    <mot-unique>بوتي</mot-unique>
    <frequence-mot>1</frequence-mot>
  </MOT>
  <MOT>
    <mot-unique>بوخدو</mot-unique>
    <frequence-mot>1</frequence-mot>
  </MOT>
  <MOT>
    <mot-unique>بوزة</mot-unique>
    <frequence-mot>1</frequence-mot>
  </MOT>
  <MOT>
    <mot-unique>بيتعمدو</mot-unique>
    <frequence-mot>1</frequence-mot>
  </MOT>
  <MOT>
    <mot-unique>بيجننو</mot-unique>
    <frequence-mot>1</frequence-mot>
  </MOT>
  <MOT>
    <mot-unique>بيجيو</mot-unique>
    <frequence-mot>1</frequence-mot>
  </MOT>
  <MOT>
    <mot-unique>بيربي</mot-unique>
    <frequence-mot>1</frequence-mot>
  </MOT>
  <MOT>
    <mot-unique>بيرجعو</mot-unique>
    <frequence-mot>1</frequence-mot>
  </MOT>
  <MOT>
    <mot-unique>بيروحو</mot-unique>
    <frequence-mot>1</frequence-mot>
  </MOT>
  <MOT>
    <mot-unique>بيشتغل</mot-unique>
    <frequence-mot>1</frequence-mot>
  </MOT>
  <MOT>
    <mot-unique>بيعطلو</mot-unique>
    <frequence-mot>1</frequence-mot>
  </MOT>
  <MOT>
    <mot-unique>بيقدرو</mot-unique>
    <frequence-mot>1</frequence-mot>
  </MOT>
  <MOT>
    <mot-unique>بيكفي</mot-unique>
    <frequence-mot>2</frequence-mot>
  </MOT>
  <MOT>
    <mot-unique>بيماطل</mot-unique>
    <frequence-mot>1</frequence-mot>
  </MOT>
  <MOT>
    <mot-unique>بيوجعوني</mot-unique>
    <frequence-mot>1</frequence-mot>
  </MOT>
  <MOT>
    <mot-unique>بيوكلو</mot-unique>
    <frequence-mot>1</frequence-mot>
  </MOT>
  <MOT>
    <mot-unique>تبط</mot-unique>
    <frequence-mot>1</frequence-mot>
  </MOT>
  <MOT>
    <mot-unique>تذكر</mot-unique>
    <frequence-mot>1</frequence-mot>
  </MOT>
  <MOT>
    <mot-unique>تسحيو</mot-unique>
    <frequence-mot>1</frequence-mot>
  </MOT>
  <MOT>
    <mot-unique>تسويق</mot-unique>
    <frequence-mot>1</frequence-mot>
  </MOT>
  <MOT>
    <mot-unique>تطلعو</mot-unique>
    <frequence-mot>1</frequence-mot>
  </MOT>
  <MOT>
    <mot-unique>تعرقل</mot-unique>
    <frequence-mot>1</frequence-mot>
  </MOT>
  <MOT>
    <mot-unique>تعطى</mot-unique>
    <frequence-mot>1</frequence-mot>
  </MOT>
  <MOT>
    <mot-unique>تعلن</mot-unique>
    <frequence-mot>1</frequence-mot>
  </MOT>
  <MOT>
    <mot-unique>تعينو</mot-unique>
    <frequence-mot>1</frequence-mot>
  </MOT>
  <MOT>
    <mot-unique>تفرجني</mot-unique>
    <frequence-mot>2</frequence-mot>
  </MOT>
  <MOT>
    <mot-unique>تفقدها</mot-unique>
    <frequence-mot>1</frequence-mot>
  </MOT>
  <MOT>
    <mot-unique>تقيمه</mot-unique>
    <frequence-mot>1</frequence-mot>
  </MOT>
  <MOT>
    <mot-unique>تلافيه</mot-unique>
    <frequence-mot>1</frequence-mot>
  </MOT>
  <MOT>
    <mot-unique>تلقون</mot-unique>
    <frequence-mot>1</frequence-mot>
  </MOT>
  <MOT>
    <mot-unique>توخد</mot-unique>
    <frequence-mot>1</frequence-mot>
  </MOT>
  <MOT>
    <mot-unique>توخده</mot-unique>
    <frequence-mot>1</frequence-mot>
  </MOT>
  <MOT>
    <mot-unique>توخدها</mot-unique>
    <frequence-mot>1</frequence-mot>
  </MOT>
  <MOT>
    <mot-unique>توخذ</mot-unique>
    <frequence-mot>3</frequence-mot>
  </MOT>
  <MOT>
    <mot-unique>جكيت</mot-unique>
    <frequence-mot>1</frequence-mot>
  </MOT>
  <MOT>
    <mot-unique>جوات</mot-unique>
    <frequence-mot>1</frequence-mot>
  </MOT>
  <MOT>
    <mot-unique>جية</mot-unique>
    <frequence-mot>1</frequence-mot>
  </MOT>
  <MOT>
    <mot-unique>حاص</mot-unique>
    <frequence-mot>1</frequence-mot>
  </MOT>
  <MOT>
    <mot-unique>حجمي</mot-unique>
    <frequence-mot>1</frequence-mot>
  </MOT>
  <MOT>
    <mot-unique>حزا</mot-unique>
    <frequence-mot>1</frequence-mot>
  </MOT>
  <MOT>
    <mot-unique>حطتها</mot-unique>
    <frequence-mot>1</frequence-mot>
  </MOT>
  <MOT>
    <mot-unique>حكالي</mot-unique>
    <frequence-mot>1</frequence-mot>
  </MOT>
  <MOT>
    <mot-unique>حكت</mot-unique>
    <frequence-mot>1</frequence-mot>
  </MOT>
  <MOT>
    <mot-unique>حيث</mot-unique>
    <frequence-mot>1</frequence-mot>
  </MOT>
  <MOT>
    <mot-unique>خلصو</mot-unique>
    <frequence-mot>1</frequence-mot>
  </MOT>
  <MOT>
    <mot-unique>خليلك</mot-unique>
    <frequence-mot>1</frequence-mot>
  </MOT>
  <MOT>
    <mot-unique>دخوليتك</mot-unique>
    <frequence-mot>1</frequence-mot>
  </MOT>
  <MOT>
    <mot-unique>دولارت</mot-unique>
    <frequence-mot>1</frequence-mot>
  </MOT>
  <MOT>
    <mot-unique>ربطة</mot-unique>
    <frequence-mot>1</frequence-mot>
  </MOT>
  <MOT>
    <mot-unique>رحل</mot-unique>
    <frequence-mot>1</frequence-mot>
  </MOT>
  <MOT>
    <mot-unique>رعاية</mot-unique>
    <frequence-mot>1</frequence-mot>
  </MOT>
  <MOT>
    <mot-unique>زحلق</mot-unique>
    <frequence-mot>1</frequence-mot>
  </MOT>
  <MOT>
    <mot-unique>زريعة</mot-unique>
    <frequence-mot>1</frequence-mot>
  </MOT>
  <MOT>
    <mot-unique>زواية</mot-unique>
    <frequence-mot>1</frequence-mot>
  </MOT>
  <MOT>
    <mot-unique>سااتي</mot-unique>
    <frequence-mot>1</frequence-mot>
  </MOT>
  <MOT>
    <mot-unique>ساعت</mot-unique>
    <frequence-mot>1</frequence-mot>
  </MOT>
  <MOT>
    <mot-unique>سعراتو</mot-unique>
    <frequence-mot>1</frequence-mot>
  </MOT>
  <MOT>
    <mot-unique>سنتميتر</mot-unique>
    <frequence-mot>1</frequence-mot>
  </MOT>
  <MOT>
    <mot-unique>سينت</mot-unique>
    <frequence-mot>1</frequence-mot>
  </MOT>
  <MOT>
    <mot-unique>شاملو</mot-unique>
    <frequence-mot>1</frequence-mot>
  </MOT>
  <MOT>
    <mot-unique>شروط</mot-unique>
    <frequence-mot>1</frequence-mot>
  </MOT>
  <MOT>
    <mot-unique>شروطك</mot-unique>
    <frequence-mot>1</frequence-mot>
  </MOT>
  <MOT>
    <mot-unique>شغلهم</mot-unique>
    <frequence-mot>1</frequence-mot>
  </MOT>
  <MOT>
    <mot-unique>شنجهاي</mot-unique>
    <frequence-mot>1</frequence-mot>
  </MOT>
  <MOT>
    <mot-unique>شوجيبوكرو</mot-unique>
    <frequence-mot>1</frequence-mot>
  </MOT>
  <MOT>
    <mot-unique>صراف</mot-unique>
    <frequence-mot>2</frequence-mot>
  </MOT>
  <MOT>
    <mot-unique>صغية</mot-unique>
    <frequence-mot>1</frequence-mot>
  </MOT>
  <MOT>
    <mot-unique>ضليت</mot-unique>
    <frequence-mot>1</frequence-mot>
  </MOT>
  <MOT>
    <mot-unique>طقت</mot-unique>
    <frequence-mot>1</frequence-mot>
  </MOT>
  <MOT>
    <mot-unique>ظ</mot-unique>
    <frequence-mot>1</frequence-mot>
  </MOT>
  <MOT>
    <mot-unique>عرباية</mot-unique>
    <frequence-mot>1</frequence-mot>
  </MOT>
  <MOT>
    <mot-unique>عطور</mot-unique>
    <frequence-mot>1</frequence-mot>
  </MOT>
  <MOT>
    <mot-unique>عندكو</mot-unique>
    <frequence-mot>1</frequence-mot>
  </MOT>
  <MOT>
    <mot-unique>غلرفة</mot-unique>
    <frequence-mot>1</frequence-mot>
  </MOT>
  <MOT>
    <mot-unique>فخم</mot-unique>
    <frequence-mot>1</frequence-mot>
  </MOT>
  <MOT>
    <mot-unique>فغرفة</mot-unique>
    <frequence-mot>1</frequence-mot>
  </MOT>
  <MOT>
    <mot-unique>فكرت</mot-unique>
    <frequence-mot>1</frequence-mot>
  </MOT>
  <MOT>
    <mot-unique>قة</mot-unique>
    <frequence-mot>1</frequence-mot>
  </MOT>
  <MOT>
    <mot-unique>قلتلو</mot-unique>
    <frequence-mot>1</frequence-mot>
  </MOT>
  <MOT>
    <mot-unique>كتحلاي</mot-unique>
    <frequence-mot>1</frequence-mot>
  </MOT>
  <MOT>
    <mot-unique>كثيير</mot-unique>
    <frequence-mot>1</frequence-mot>
  </MOT>
  <MOT>
    <mot-unique>لابيض</mot-unique>
    <frequence-mot>1</frequence-mot>
  </MOT>
  <MOT>
    <mot-unique>لازن</mot-unique>
    <frequence-mot>1</frequence-mot>
  </MOT>
  <MOT>
    <mot-unique>لساتك</mot-unique>
    <frequence-mot>1</frequence-mot>
  </MOT>
  <MOT>
    <mot-unique>لساتها</mot-unique>
    <frequence-mot>1</frequence-mot>
  </MOT>
  <MOT>
    <mot-unique>لشحنها</mot-unique>
    <frequence-mot>1</frequence-mot>
  </MOT>
  <MOT>
    <mot-unique>لعة</mot-unique>
    <frequence-mot>1</frequence-mot>
  </MOT>
  <MOT>
    <mot-unique>لقرية</mot-unique>
    <frequence-mot>1</frequence-mot>
  </MOT>
  <MOT>
    <mot-unique>لقلبان</mot-unique>
    <frequence-mot>1</frequence-mot>
  </MOT>
  <MOT>
    <mot-unique>للاجهزة</mot-unique>
    <frequence-mot>1</frequence-mot>
  </MOT>
  <MOT>
    <mot-unique>للتاامين</mot-unique>
    <frequence-mot>1</frequence-mot>
  </MOT>
  <MOT>
    <mot-unique>للتغيير</mot-unique>
    <frequence-mot>1</frequence-mot>
  </MOT>
  <MOT>
    <mot-unique>للثم</mot-unique>
    <frequence-mot>1</frequence-mot>
  </MOT>
  <MOT>
    <mot-unique>للطلعة</mot-unique>
    <frequence-mot>1</frequence-mot>
  </MOT>
  <MOT>
    <mot-unique>للقرية</mot-unique>
    <frequence-mot>1</frequence-mot>
  </MOT>
  <MOT>
    <mot-unique>للكبار</mot-unique>
    <frequence-mot>1</frequence-mot>
  </MOT>
  <MOT>
    <mot-unique>للمعالم</mot-unique>
    <frequence-mot>1</frequence-mot>
  </MOT>
  <MOT>
    <mot-unique>للنشاط</mot-unique>
    <frequence-mot>1</frequence-mot>
  </MOT>
  <MOT>
    <mot-unique>للوصل</mot-unique>
    <frequence-mot>1</frequence-mot>
  </MOT>
  <MOT>
    <mot-unique>لليابانيين</mot-unique>
    <frequence-mot>1</frequence-mot>
  </MOT>
  <MOT>
    <mot-unique>لمهمة</mot-unique>
    <frequence-mot>1</frequence-mot>
  </MOT>
  <MOT>
    <mot-unique>لنمرة</mot-unique>
    <frequence-mot>1</frequence-mot>
  </MOT>
  <MOT>
    <mot-unique>لوحاتك</mot-unique>
    <frequence-mot>1</frequence-mot>
  </MOT>
  <MOT>
    <mot-unique>مؤدب</mot-unique>
    <frequence-mot>1</frequence-mot>
  </MOT>
  <MOT>
    <mot-unique>ماخوذة</mot-unique>
    <frequence-mot>1</frequence-mot>
  </MOT>
  <MOT>
    <mot-unique>مبهر</mot-unique>
    <frequence-mot>1</frequence-mot>
  </MOT>
  <MOT>
    <mot-unique>مجتمعهم</mot-unique>
    <frequence-mot>1</frequence-mot>
  </MOT>
  <MOT>
    <mot-unique>مجواهرتي</mot-unique>
    <frequence-mot>1</frequence-mot>
  </MOT>
  <MOT>
    <mot-unique>مجوز</mot-unique>
    <frequence-mot>1</frequence-mot>
  </MOT>
  <MOT>
    <mot-unique>مخط</mot-unique>
    <frequence-mot>1</frequence-mot>
  </MOT>
  <MOT>
    <mot-unique>مزعه</mot-unique>
    <frequence-mot>1</frequence-mot>
  </MOT>
  <MOT>
    <mot-unique>مصممين</mot-unique>
    <frequence-mot>1</frequence-mot>
  </MOT>
  <MOT>
    <mot-unique>معتي</mot-unique>
    <frequence-mot>1</frequence-mot>
  </MOT>
  <MOT>
    <mot-unique>معطلة</mot-unique>
    <frequence-mot>1</frequence-mot>
  </MOT>
  <MOT>
    <mot-unique>معكو</mot-unique>
    <frequence-mot>1</frequence-mot>
  </MOT>
  <MOT>
    <mot-unique>معلف</mot-unique>
    <frequence-mot>1</frequence-mot>
  </MOT>
  <MOT>
    <mot-unique>معهم</mot-unique>
    <frequence-mot>1</frequence-mot>
  </MOT>
  <MOT>
    <mot-unique>مفضي</mot-unique>
    <frequence-mot>1</frequence-mot>
  </MOT>
  <MOT>
    <mot-unique>مكاتبكو</mot-unique>
    <frequence-mot>1</frequence-mot>
  </MOT>
  <MOT>
    <mot-unique>ملحقك</mot-unique>
    <frequence-mot>1</frequence-mot>
  </MOT>
  <MOT>
    <mot-unique>ممزع</mot-unique>
    <frequence-mot>1</frequence-mot>
  </MOT>
  <MOT>
    <mot-unique>مناسبني</mot-unique>
    <frequence-mot>1</frequence-mot>
  </MOT>
  <MOT>
    <mot-unique>ميتروبيلتون</mot-unique>
    <frequence-mot>1</frequence-mot>
  </MOT>
  <MOT>
    <mot-unique>ناسبتني</mot-unique>
    <frequence-mot>1</frequence-mot>
  </MOT>
  <MOT>
    <mot-unique>نحضره</mot-unique>
    <frequence-mot>1</frequence-mot>
  </MOT>
  <MOT>
    <mot-unique>نخدمكو</mot-unique>
    <frequence-mot>1</frequence-mot>
  </MOT>
  <MOT>
    <mot-unique>نصوصو</mot-unique>
    <frequence-mot>1</frequence-mot>
  </MOT>
  <MOT>
    <mot-unique>نضيفكو</mot-unique>
    <frequence-mot>1</frequence-mot>
  </MOT>
  <MOT>
    <mot-unique>نط</mot-unique>
    <frequence-mot>1</frequence-mot>
  </MOT>
  <MOT>
    <mot-unique>نفسو</mot-unique>
    <frequence-mot>1</frequence-mot>
  </MOT>
  <MOT>
    <mot-unique>نوخده</mot-unique>
    <frequence-mot>1</frequence-mot>
  </MOT>
  <MOT>
    <mot-unique>نوكل</mot-unique>
    <frequence-mot>1</frequence-mot>
  </MOT>
  <MOT>
    <mot-unique>نيويرك</mot-unique>
    <frequence-mot>2</frequence-mot>
  </MOT>
  <MOT>
    <mot-unique>هاررودس</mot-unique>
    <frequence-mot>1</frequence-mot>
  </MOT>
  <MOT>
    <mot-unique>هالعنوان</mot-unique>
    <frequence-mot>1</frequence-mot>
  </MOT>
  <MOT>
    <mot-unique>هالفطور</mot-unique>
    <frequence-mot>1</frequence-mot>
  </MOT>
  <MOT>
    <mot-unique>هاوااي</mot-unique>
    <frequence-mot>1</frequence-mot>
  </MOT>
  <MOT>
    <mot-unique>هجئها</mot-unique>
    <frequence-mot>1</frequence-mot>
  </MOT>
  <MOT>
    <mot-unique>هجم</mot-unique>
    <frequence-mot>1</frequence-mot>
  </MOT>
  <MOT>
    <mot-unique>هد</mot-unique>
    <frequence-mot>1</frequence-mot>
  </MOT>
  <MOT>
    <mot-unique>هديتها</mot-unique>
    <frequence-mot>1</frequence-mot>
  </MOT>
  <MOT>
    <mot-unique>واتناب</mot-unique>
    <frequence-mot>1</frequence-mot>
  </MOT>
  <MOT>
    <mot-unique>وايمنالو</mot-unique>
    <frequence-mot>1</frequence-mot>
  </MOT>
  <MOT>
    <mot-unique>وبرتقان</mot-unique>
    <frequence-mot>1</frequence-mot>
  </MOT>
  <MOT>
    <mot-unique>وبنطلع</mot-unique>
    <frequence-mot>1</frequence-mot>
  </MOT>
  <MOT>
    <mot-unique>وحد</mot-unique>
    <frequence-mot>1</frequence-mot>
  </MOT>
  <MOT>
    <mot-unique>وحكى</mot-unique>
    <frequence-mot>1</frequence-mot>
  </MOT>
  <MOT>
    <mot-unique>ورقمو</mot-unique>
    <frequence-mot>1</frequence-mot>
  </MOT>
  <MOT>
    <mot-unique>وصلو</mot-unique>
    <frequence-mot>1</frequence-mot>
  </MOT>
  <MOT>
    <mot-unique>يبطلو</mot-unique>
    <frequence-mot>1</frequence-mot>
  </MOT>
  <MOT>
    <mot-unique>يتنظف</mot-unique>
    <frequence-mot>1</frequence-mot>
  </MOT>
  <MOT>
    <mot-unique>يجيبلولنا</mot-unique>
    <frequence-mot>1</frequence-mot>
  </MOT>
  <MOT>
    <mot-unique>يحبو</mot-unique>
    <frequence-mot>1</frequence-mot>
  </MOT>
  <MOT>
    <mot-unique>يعيشو</mot-unique>
    <frequence-mot>1</frequence-mot>
  </MOT>
  <MOT>
    <mot-unique>يمادا</mot-unique>
    <frequence-mot>1</frequence-mot>
  </MOT>
  <MOT>
    <mot-unique>ينبعثلك</mot-unique>
    <frequence-mot>1</frequence-mot>
  </MOT>
  <MOT>
    <mot-unique>ينسحبو</mot-unique>
    <frequence-mot>1</frequence-mot>
  </MOT>
  <MOT>
    <mot-unique>يوخذو</mot-unique>
    <frequence-mot>1</frequence-mot>
  </MOT>
  <MOT>
    <mot-unique>يونيو</mot-unique>
    <frequence-mot>1</frequence-mot>
  </MOT>
</vocabulaires>
